mausify/__init__.py
mausify/main.py
mausify-0.0.2.dist-info/LICENSE
mausify-0.0.2.dist-info/METADATA
mausify-0.0.2.dist-info/WHEEL
mausify-0.0.2.dist-info/RECORD
