Metadata-Version: 2.1
Name: mausify
Version: 0.0.2
Summary: Wraps cli commands for use in python
Author: fergus
Author-email: fergusfettes@gmail.com
Requires-Python: >=3.8.1,<3.13
Classifier: Programming Language :: Python :: 3
Classifier: Programming Language :: Python :: 3.9
Classifier: Programming Language :: Python :: 3.10
Classifier: Programming Language :: Python :: 3.11
Classifier: Programming Language :: Python :: 3.12
Requires-Dist: click (>=8.1.3,<9.0.0)
Requires-Dist: click-shell (>=2.1,<3.0)
Requires-Dist: pyyaml (>=6.0,<7.0)
Requires-Dist: requests (>=2.32.3,<3.0.0)
Requires-Dist: rich (>=13.3.5,<14.0.0)
Requires-Dist: typer (>=0.12.4,<0.13.0)
Requires-Dist: urllib3 (>=2.2.3,<3.0.0)
